README.md
pyproject.toml
setup.py
insightface/__init__.py
insightface/app/__init__.py
insightface/app/common.py
insightface/app/face_analysis.py
insightface/app/intangles_face_analysis.py
insightface/app/mask_renderer.py
insightface/commands/__init__.py
insightface/commands/insightface_cli.py
insightface/commands/model_download.py
insightface/commands/rec_add_mask_param.py
insightface/data/__init__.py
insightface/data/image.py
insightface/data/pickle_object.py
insightface/data/rec_builder.py
insightface/data/images/Tom_Hanks_54745.png
insightface/data/images/mask_black.jpg
insightface/data/images/mask_blue.jpg
insightface/data/images/mask_green.jpg
insightface/data/images/mask_white.jpg
insightface/data/images/t1.jpg
insightface/data/objects/meanshape_68.pkl
insightface/model_zoo/__init__.py
insightface/model_zoo/arcface_onnx.py
insightface/model_zoo/attribute.py
insightface/model_zoo/inswapper.py
insightface/model_zoo/landmark.py
insightface/model_zoo/model_store.py
insightface/model_zoo/model_zoo.py
insightface/model_zoo/retinaface.py
insightface/model_zoo/scrfd.py
insightface/thirdparty/__init__.py
insightface/thirdparty/face3d/__init__.py
insightface/thirdparty/face3d/mesh/__init__.py
insightface/thirdparty/face3d/mesh/io.py
insightface/thirdparty/face3d/mesh/light.py
insightface/thirdparty/face3d/mesh/render.py
insightface/thirdparty/face3d/mesh/transform.py
insightface/thirdparty/face3d/mesh/vis.py
insightface/thirdparty/face3d/mesh/cython/mesh_core.cpp
insightface/thirdparty/face3d/mesh/cython/mesh_core.h
insightface/thirdparty/face3d/mesh/cython/mesh_core_cython.c
insightface/thirdparty/face3d/mesh/cython/mesh_core_cython.cpp
insightface/thirdparty/face3d/mesh/cython/mesh_core_cython.pyx
insightface/thirdparty/face3d/mesh/cython/setup.py
insightface/thirdparty/face3d/mesh_numpy/__init__.py
insightface/thirdparty/face3d/mesh_numpy/io.py
insightface/thirdparty/face3d/mesh_numpy/light.py
insightface/thirdparty/face3d/mesh_numpy/render.py
intangles_insightface.egg-info/PKG-INFO
intangles_insightface.egg-info/SOURCES.txt
intangles_insightface.egg-info/dependency_links.txt
intangles_insightface.egg-info/entry_points.txt
intangles_insightface.egg-info/requires.txt
intangles_insightface.egg-info/top_level.txt
intangles_insightface.egg-info/zip-safe