Metadata-Version: 2.1
Name: intangles-insightface
Version: 0.7.3.4
Summary: Intangles-InsightFace Python Library forked by Intangles
Home-page: https://github.com/Intangles/intangles-insightface
Author: InsightFace Contributors
Author-email: ssatyam4753@gmail.com
License: MIT
Requires-Dist: numpy
Requires-Dist: onnx
Requires-Dist: tqdm
Requires-Dist: requests
Requires-Dist: matplotlib
Requires-Dist: Pillow
Requires-Dist: scipy
Requires-Dist: scikit-learn
Requires-Dist: scikit-image
Requires-Dist: easydict
Requires-Dist: cython
Requires-Dist: albumentations
Requires-Dist: prettytable
